{"characters":[{"id":"ryu","name":"リュウ"},{"id":"ken","name":"ケン"},{"id":"chunli","name":"春麗"},{"id":"luke","name":"ルーク"},{"id":"jamie","name":"ジェイミー"},{"id":"manon","name":"マノン"},{"id":"kimberly","name":"キンバリー"},{"id":"marisa","name":"マリーザ"},{"id":"jp","name":"JP"},{"id":"juri","name":"ジュリ"},{"id":"deejay","name":"ディージェイ"},{"id":"cammy","name":"キャミィ"},{"id":"lily","name":"リリー"},{"id":"zangief","name":"ザンギエフ"},{"id":"dhalsim","name":"ダルシム"},{"id":"honda","name":"エドモンド本田"},{"id":"blanka","name":"ブランカ"},{"id":"guile","name":"ガイル"},{"id":"aki","name":"A.K.I."},{"id":"rashid","name":"ラシード"},{"id":"ed","name":"エド"},{"id":"akuma","name":"豪鬼"},{"id":"bison","name":"ベガ"},{"id":"terry","name":"テリー"},{"id":"mai","name":"不知火舞"},{"id":"elena","name":"エレナ"},{"id":"sagat","name":"サガット"},{"id":"cviper","name":"C.ヴァイパー"},{"id":"alex","name":"アレックス"},{"id":"ingrid","name":"イングリッド"}],"combos":[{"id":"aki-crmk-hit","character":"aki","starter":"屈中K","situation":"通常ヒット","damageClassic":2230,"damageModern":2010,"drive":0,"superArt":0,"difficulty":3,"notes":"差し返しサンプル。","route":["屈中K","蛇軽功","凶襲突"],"tags":["中央","差し返し"]},{"id":"aki-mp-hit","character":"aki","starter":"立中P","situation":"通常ヒット","damageClassic":2520,"damageModern":2270,"drive":0,"superArt":0,"difficulty":3,"notes":"毒状態別に追加しやすいサンプル。","route":["立中P","蛇頭鞭","凶襲突"],"tags":["中央","毒"]},{"id":"akuma-mp-hit","character":"akuma","starter":"立中P","situation":"通常ヒット","damageClassic":2780,"damageModern":2500,"drive":0,"superArt":0,"difficulty":3,"notes":"中央確認サンプル。","route":["立中P","竜巻斬空脚","豪昇龍拳"],"tags":["中央","安定"]},{"id":"akuma-hp-pc","character":"akuma","starter":"立強P","situation":"パニッシュカウンター","damageClassic":3660,"damageModern":3290,"drive":0,"superArt":0,"difficulty":4,"notes":"確反サンプル。","route":["立強P","百鬼襲","豪昇龍拳"],"tags":["パニッシュカウンター","高火力"]},{"id":"alex-mp-hit","character":"alex","starter":"立中P","situation":"通常ヒット","damageClassic":2690,"damageModern":2420,"drive":0,"superArt":0,"difficulty":3,"notes":"中央確認サンプル。","route":["立中P","フラッシュチョップ","エアスタンピート"],"tags":["中央","安定"]},{"id":"alex-hp-pc","character":"alex","starter":"立強P","situation":"パニッシュカウンター","damageClassic":3610,"damageModern":3250,"drive":0,"superArt":0,"difficulty":4,"notes":"確反サンプル。","route":["立強P","スラッシュエルボー","パワーボム"],"tags":["パニッシュカウンター","高火力"]},{"id":"bison-crmk-hit","character":"bison","starter":"屈中K","situation":"通常ヒット","damageClassic":2240,"damageModern":2020,"drive":0,"superArt":0,"difficulty":2,"notes":"差し返しサンプル。","route":["屈中K","ダブルニープレス"],"tags":["中央","差し返し"]},{"id":"bison-mp-hit","character":"bison","starter":"立中P","situation":"通常ヒット","damageClassic":2760,"damageModern":2480,"drive":0,"superArt":0,"difficulty":3,"notes":"中央確認サンプル。","route":["立中P","サイコクラッシャー","ダブルニープレス"],"tags":["中央","安定"]},{"id":"blanka-crmk-hit","character":"blanka","starter":"屈中K","situation":"通常ヒット","damageClassic":2130,"damageModern":1920,"drive":0,"superArt":0,"difficulty":2,"notes":"差し返しサンプル。","route":["屈中K","ローリングアタック"],"tags":["中央","差し返し"]},{"id":"blanka-mp-hit","character":"blanka","starter":"立中P","situation":"通常ヒット","damageClassic":2580,"damageModern":2320,"drive":0,"superArt":0,"difficulty":3,"notes":"中央確認サンプル。","route":["立中P","エレクトリックサンダー","ローリングアタック"],"tags":["中央","安定"]},{"id":"cammy-crmk","character":"cammy","starter":"屈中K","situation":"通常ヒット","damageClassic":2210,"damageModern":1990,"drive":0,"superArt":0,"difficulty":2,"notes":"中距離の確認用サンプル。","route":["屈中K","スパイラルアロー","キャノンスパイク"],"tags":["中央","差し返し"]},{"id":"cammy-mp-hit","character":"cammy","starter":"立中P","situation":"通常ヒット","damageClassic":2510,"damageModern":2260,"drive":0,"superArt":0,"difficulty":2,"notes":"近距離確認サンプル。","route":["立中P","スパイラルアロー","キャノンスパイク"],"tags":["中央","安定"]},{"id":"chunli-crmk-hit","character":"chunli","starter":"屈中K","situation":"通常ヒット","damageClassic":2320,"damageModern":2090,"drive":0,"superArt":0,"difficulty":3,"notes":"差し返し用の低コストサンプル。","route":["屈中K","百裂脚","天昇脚"],"tags":["中央","差し返し"]},{"id":"chunli-corner","character":"chunli","starter":"立中P","situation":"画面端 通常ヒット","damageClassic":3560,"damageModern":3200,"drive":2,"superArt":0,"difficulty":3,"notes":"端での火力と消費のバランス候補。","route":["立中P","百裂脚","OD気功拳","天昇脚"],"tags":["バランス","画面端"]},{"id":"cviper-mp-hit","character":"cviper","starter":"立中P","situation":"通常ヒット","damageClassic":2660,"damageModern":2390,"drive":0,"superArt":0,"difficulty":3,"notes":"中央確認サンプル。","route":["立中P","サンダーナックル","バーニングキック"],"tags":["中央","安定"]},{"id":"cviper-hp-pc","character":"cviper","starter":"立強P","situation":"パニッシュカウンター","damageClassic":3520,"damageModern":3170,"drive":0,"superArt":0,"difficulty":4,"notes":"確反サンプル。","route":["立強P","セイスモハンマー","サンダーナックル"],"tags":["パニッシュカウンター","高火力"]},{"id":"deejay-crmk-hit","character":"deejay","starter":"屈中K","situation":"通常ヒット","damageClassic":2290,"damageModern":2060,"drive":0,"superArt":0,"difficulty":3,"notes":"差し返しサンプル。","route":["屈中K","ソバット","ジャックナイフマキシマム"],"tags":["中央","差し返し"]},{"id":"deejay-mp-hit","character":"deejay","starter":"立中P","situation":"通常ヒット","damageClassic":2740,"damageModern":2470,"drive":0,"superArt":0,"difficulty":3,"notes":"中央確認サンプル。","route":["立中P","マシンガンアッパー","ジャックナイフマキシマム"],"tags":["中央","安定"]},{"id":"dhalsim-crmp-hit","character":"dhalsim","starter":"屈中P","situation":"通常ヒット","damageClassic":2140,"damageModern":1930,"drive":0,"superArt":0,"difficulty":3,"notes":"位置調整込みのサンプル。","route":["屈中P","ヨガフレイム","ヨガテレポート"],"tags":["中央","位置入替"]},{"id":"dhalsim-mp-hit","character":"dhalsim","starter":"立中P","situation":"通常ヒット","damageClassic":2220,"damageModern":2000,"drive":0,"superArt":0,"difficulty":3,"notes":"距離別に増やせるサンプル。","route":["立中P","ヨガフレイム","ヨガブラスト"],"tags":["中央","低コスト"]},{"id":"ed-crlk-hit","character":"ed","starter":"屈弱K","situation":"通常ヒット","damageClassic":1440,"damageModern":1300,"drive":0,"superArt":0,"difficulty":2,"notes":"小技始動サンプル。","route":["屈弱K","屈弱P","サイコアッパー"],"tags":["安定","小技"]},{"id":"ed-mp-hit","character":"ed","starter":"立中P","situation":"通常ヒット","damageClassic":2590,"damageModern":2330,"drive":0,"superArt":0,"difficulty":2,"notes":"中央確認サンプル。","route":["立中P","サイコブリッツ","サイコアッパー"],"tags":["中央","安定"]},{"id":"elena-crmk-hit","character":"elena","starter":"屈中K","situation":"通常ヒット","damageClassic":2190,"damageModern":1970,"drive":0,"superArt":0,"difficulty":3,"notes":"差し返しサンプル。","route":["屈中K","リンクステイル","スクラッチホイール"],"tags":["中央","差し返し"]},{"id":"elena-mp-hit","character":"elena","starter":"立中P","situation":"通常ヒット","damageClassic":2510,"damageModern":2260,"drive":0,"superArt":0,"difficulty":3,"notes":"中央確認サンプル。","route":["立中P","ライノホーン","スクラッチホイール"],"tags":["中央","安定"]},{"id":"guile-crmp-hit","character":"guile","starter":"屈中P","situation":"通常ヒット","damageClassic":2410,"damageModern":2170,"drive":0,"superArt":0,"difficulty":3,"notes":"溜め確認サンプル。","route":["屈中P","ソニックブーム","サマーソルトキック"],"tags":["中央","安定"]},{"id":"guile-boom","character":"guile","starter":"立中P","situation":"通常ヒット","damageClassic":2480,"damageModern":2230,"drive":0,"superArt":0,"difficulty":3,"notes":"溜め状況に応じて詳細ルートを追加できます。","route":["立中P","ソニックブーム","サマーソルトキック"],"tags":["中央","安定"]},{"id":"honda-mp-hit","character":"honda","starter":"立中P","situation":"通常ヒット","damageClassic":2730,"damageModern":2460,"drive":0,"superArt":0,"difficulty":2,"notes":"張り手確認サンプル。","route":["立中P","百裂張り手","スーパー頭突き"],"tags":["中央","安定"]},{"id":"honda-hp-pc","character":"honda","starter":"立強P","situation":"パニッシュカウンター","damageClassic":3420,"damageModern":3080,"drive":0,"superArt":0,"difficulty":3,"notes":"確反サンプル。","route":["立強P","大砲","スーパー百貫落とし"],"tags":["パニッシュカウンター","中央"]},{"id":"ingrid-crmk-hit","character":"ingrid","starter":"屈中K","situation":"通常ヒット","damageClassic":2200,"damageModern":1980,"drive":0,"superArt":0,"difficulty":3,"notes":"差し返しサンプル。","route":["屈中K","サンアーチ","サンアッパー"],"tags":["中央","差し返し"]},{"id":"ingrid-mp-hit","character":"ingrid","starter":"立中P","situation":"通常ヒット","damageClassic":2540,"damageModern":2290,"drive":0,"superArt":0,"difficulty":3,"notes":"中央確認サンプル。","route":["立中P","サンシュート","サンアッパー"],"tags":["中央","安定"]},{"id":"jamie-crlk-hit","character":"jamie","starter":"屈弱K","situation":"通常ヒット","damageClassic":1420,"damageModern":1280,"drive":0,"superArt":0,"difficulty":2,"notes":"小技始動のサンプル。","route":["屈弱K","屈弱P","弱流酔拳"],"tags":["安定","小技"]},{"id":"jamie-mp-hit","character":"jamie","starter":"立中P","situation":"通常ヒット","damageClassic":2420,"damageModern":2180,"drive":0,"superArt":0,"difficulty":2,"notes":"酔いレベル別の実測値に置き換えやすいサンプル。","route":["立中P","流酔拳","酔疾歩"],"tags":["中央","低コスト"]},{"id":"jp-crmp-hit","character":"jp","starter":"屈中P","situation":"通常ヒット","damageClassic":2360,"damageModern":2120,"drive":0,"superArt":0,"difficulty":3,"notes":"中央確認サンプル。","route":["屈中P","ヴィーハト","トリグラフ"],"tags":["中央","低コスト"]},{"id":"jp-mp-hit","character":"jp","starter":"立中P","situation":"通常ヒット","damageClassic":2490,"damageModern":2240,"drive":0,"superArt":0,"difficulty":3,"notes":"設置や距離別に追加しやすいサンプル。","route":["立中P","ストリボーグ","トリグラフ"],"tags":["中央","設置"]},{"id":"juri-crmk-hit","character":"juri","starter":"屈中K","situation":"通常ヒット","damageClassic":2310,"damageModern":2080,"drive":0,"superArt":0,"difficulty":2,"notes":"風破管理用サンプル。","route":["屈中K","歳破衝","強天穿輪"],"tags":["中央","差し返し"]},{"id":"juri-cmp","character":"juri","starter":"立中P","situation":"通常ヒット","damageClassic":2380,"damageModern":2140,"drive":0,"superArt":0,"difficulty":2,"notes":"風破ストックや状況別に派生データを増やせます。","route":["立中P","歳破衝","強天穿輪"],"tags":["中央","低コスト"]},{"id":"ken-crlk","character":"ken","starter":"屈弱K","situation":"通常ヒット","damageClassic":1580,"damageModern":1450,"drive":0,"superArt":0,"difficulty":2,"notes":"近距離の小技始動。安定重視の候補です。","route":["屈弱K","屈弱P","強昇龍拳"],"tags":["中央","安定"]},{"id":"ken-mp-hit","character":"ken","starter":"立中P","situation":"通常ヒット","damageClassic":2540,"damageModern":2290,"drive":0,"superArt":0,"difficulty":2,"notes":"中攻撃確認のサンプル。","route":["立中P","迅雷脚","強昇龍拳"],"tags":["中央","安定"]},{"id":"ken-pc-mid","character":"ken","starter":"立強P","situation":"中央 パニッシュカウンター","damageClassic":3180,"damageModern":2860,"drive":0,"superArt":0,"difficulty":3,"notes":"パニッシュ確認からの実戦向け候補。","route":["立強P","迅雷脚","奮迅脚","強昇龍拳"],"tags":["ノーゲージ","中央"]},{"id":"kimberly-crlk-hit","character":"kimberly","starter":"屈弱K","situation":"通常ヒット","damageClassic":1390,"damageModern":1250,"drive":0,"superArt":0,"difficulty":2,"notes":"近距離小技始動。","route":["屈弱K","屈弱P","弱武神旋風脚"],"tags":["安定","小技"]},{"id":"kimberly-mp-hit","character":"kimberly","starter":"立中P","situation":"通常ヒット","damageClassic":2510,"damageModern":2260,"drive":0,"superArt":0,"difficulty":3,"notes":"運び重視のサンプル。","route":["立中P","武神旋風脚","荒鵺捻り"],"tags":["中央","運び"]},{"id":"lily-mp-hit","character":"lily","starter":"立中P","situation":"通常ヒット","damageClassic":2480,"damageModern":2230,"drive":0,"superArt":0,"difficulty":3,"notes":"風まとい状況をタグで増やせます。","route":["立中P","コンドルウィンド","トマホークバスター"],"tags":["中央","風まとい"]},{"id":"lily-hp-pc","character":"lily","starter":"立強P","situation":"パニッシュカウンター","damageClassic":3320,"damageModern":2990,"drive":0,"superArt":0,"difficulty":3,"notes":"確反サンプル。","route":["立強P","コンドルスパイア","トマホークバスター"],"tags":["パニッシュカウンター","中央"]},{"id":"luke-jump","character":"luke","starter":"ジャンプ中K","situation":"通常ヒット","damageClassic":3320,"damageModern":3000,"drive":0,"superArt":0,"difficulty":2,"notes":"始動が通った時の安定重視。","route":["ジャンプ中K","立強P","強フラッシュナックル","強ライジングアッパー"],"tags":["中央","安定"]},{"id":"luke-crmp-hit","character":"luke","starter":"屈中P","situation":"通常ヒット","damageClassic":2740,"damageModern":2470,"drive":0,"superArt":0,"difficulty":2,"notes":"確認しやすい中央サンプル。","route":["屈中P","中フラッシュナックル","強ライジングアッパー"],"tags":["中央","安定"]},{"id":"mai-crmk-hit","character":"mai","starter":"屈中K","situation":"通常ヒット","damageClassic":2210,"damageModern":1990,"drive":0,"superArt":0,"difficulty":3,"notes":"差し返しサンプル。","route":["屈中K","花蝶扇","飛翔龍炎陣"],"tags":["中央","差し返し"]},{"id":"mai-mp-hit","character":"mai","starter":"立中P","situation":"通常ヒット","damageClassic":2590,"damageModern":2330,"drive":0,"superArt":0,"difficulty":3,"notes":"中央確認サンプル。","route":["立中P","龍炎舞","飛翔龍炎陣"],"tags":["中央","安定"]},{"id":"manon-mp-hit","character":"manon","starter":"立中P","situation":"通常ヒット","damageClassic":2620,"damageModern":2360,"drive":0,"superArt":0,"difficulty":3,"notes":"メダル状況はタグで増やせます。","route":["立中P","ランヴェルセ","マネージュドレ"],"tags":["中央","投げ派生"]},{"id":"manon-hp-pc","character":"manon","starter":"立強P","situation":"パニッシュカウンター","damageClassic":3260,"damageModern":2930,"drive":0,"superArt":0,"difficulty":3,"notes":"確定反撃用サンプル。","route":["立強P","デガジェ","ロン・ポワン"],"tags":["パニッシュカウンター","中央"]},{"id":"marisa-mp-hit","character":"marisa","starter":"立中P","situation":"通常ヒット","damageClassic":2850,"damageModern":2570,"drive":0,"superArt":0,"difficulty":2,"notes":"安定重視サンプル。","route":["立中P","ディマカイルス","グラディウス"],"tags":["中央","安定"]},{"id":"marisa-hp-pc","character":"marisa","starter":"立強P","situation":"パニッシュカウンター","damageClassic":3740,"damageModern":3370,"drive":0,"superArt":0,"difficulty":3,"notes":"大きい確反用サンプル。","route":["立強P","ファランクス","グラディウス"],"tags":["パニッシュカウンター","高火力"]},{"id":"rashid-crmk-hit","character":"rashid","starter":"屈中K","situation":"通常ヒット","damageClassic":2260,"damageModern":2030,"drive":0,"superArt":0,"difficulty":3,"notes":"差し返しサンプル。","route":["屈中K","ワールウインド・ショット","スピニングミキサー"],"tags":["中央","差し返し"]},{"id":"rashid-mp-hit","character":"rashid","starter":"立中P","situation":"通常ヒット","damageClassic":2680,"damageModern":2410,"drive":0,"superArt":0,"difficulty":3,"notes":"運び重視サンプル。","route":["立中P","イーグルスパイク","スピニングミキサー"],"tags":["中央","運び"]},{"id":"ryu-cmp-mid","character":"ryu","starter":"屈中P","situation":"通常ヒット","damageClassic":2460,"damageModern":2250,"drive":0,"superArt":0,"difficulty":2,"notes":"基本の確認用ルート。クラシックとモダンの値を別々に登録できます。","route":["屈中P","中足刀","強昇龍拳"],"tags":["中央","低コスト"]},{"id":"ryu-cmp-spend","character":"ryu","starter":"屈中P","situation":"通常ヒット","damageClassic":3920,"damageModern":3550,"drive":2,"superArt":3,"difficulty":4,"notes":"ゲージを使って倒し切りを狙う候補。モダン選択時はモダン用ダメージで比較されます。","route":["屈中P","OD足刀","中竜巻","真空波動拳"],"tags":["中央","最大寄り"]},{"id":"ryu-corner-pc","character":"ryu","starter":"立強P","situation":"画面端 パニッシュカウンター","damageClassic":3820,"damageModern":3440,"drive":0,"superArt":0,"difficulty":4,"notes":"端のノーゲージ高火力候補。実測値に置き換える前提のサンプルです。","route":["立強P","大ゴス","屈強P","強竜巻","強昇龍拳"],"tags":["パニッシュカウンター","画面端"]},{"id":"ryu-hp-pc","character":"ryu","starter":"立強P","situation":"画面端 パニッシュカウンター","damageClassic":3820,"damageModern":3440,"drive":0,"superArt":0,"difficulty":4,"notes":"端の高火力サンプル。","route":["立強P","大ゴス","屈強P","強竜巻","強昇龍拳"],"tags":["パニッシュカウンター","画面端"]},{"id":"sagat-crmk-hit","character":"sagat","starter":"屈中K","situation":"通常ヒット","damageClassic":2320,"damageModern":2090,"drive":0,"superArt":0,"difficulty":3,"notes":"差し返しサンプル。","route":["屈中K","タイガーショット","タイガーアッパーカット"],"tags":["中央","差し返し"]},{"id":"sagat-mp-hit","character":"sagat","starter":"立中P","situation":"通常ヒット","damageClassic":2780,"damageModern":2500,"drive":0,"superArt":0,"difficulty":3,"notes":"中央確認サンプル。","route":["立中P","タイガーニー","タイガーアッパーカット"],"tags":["中央","安定"]},{"id":"terry-crmk-hit","character":"terry","starter":"屈中K","situation":"通常ヒット","damageClassic":2260,"damageModern":2030,"drive":0,"superArt":0,"difficulty":3,"notes":"差し返しサンプル。","route":["屈中K","クラックシュート","ライジングタックル"],"tags":["中央","差し返し"]},{"id":"terry-mp-hit","character":"terry","starter":"立中P","situation":"通常ヒット","damageClassic":2650,"damageModern":2390,"drive":0,"superArt":0,"difficulty":2,"notes":"中央確認サンプル。","route":["立中P","バーンナックル","ライジングタックル"],"tags":["中央","安定"]},{"id":"zangief-mp-hit","character":"zangief","starter":"立中P","situation":"通常ヒット","damageClassic":2190,"damageModern":1970,"drive":0,"superArt":0,"difficulty":2,"notes":"近距離確認サンプル。","route":["立中P","ダブルラリアット"],"tags":["中央","低コスト"]},{"id":"zangief-hp-pc","character":"zangief","starter":"立強P","situation":"パニッシュカウンター","damageClassic":3510,"damageModern":3160,"drive":0,"superArt":0,"difficulty":4,"notes":"大きい反撃用サンプル。","route":["立強P","ボルシチダイナマイト"],"tags":["パニッシュカウンター","高火力"]}]}
